{
  "Instance": {
    "Ground_1": "Asset/Json/Ground_1/constant.json",
    "Ground_10": "Asset/Json/Ground_10/constant.json",
    "Ground_11": "Asset/Json/Ground_11/constant.json",
    "Ground_12": "Asset/Json/Ground_12/constant.json",
    "Ground_2": "Asset/Json/Ground_2/constant.json",
    "Ground_3": "Asset/Json/Ground_3/constant.json",
    "Ground_4": "Asset/Json/Ground_4/constant.json",
    "Ground_5": "Asset/Json/Ground_5/constant.json",
    "Ground_6": "Asset/Json/Ground_6/constant.json",
    "Ground_7": "Asset/Json/Ground_7/constant.json",
    "Ground_8": "Asset/Json/Ground_8/constant.json",
    "Ground_9": "Asset/Json/Ground_9/constant.json",
    "MainCamera": "Asset/Json/MainCamera/constant.json",
    "NeonBuilding_1": "Asset/Json/NeonBuilding_1/constant.json",
    "NeonBuilding_2": "Asset/Json/NeonBuilding_2/constant.json",
    "NeonBuilding_3": "Asset/Json/NeonBuilding_3/constant.json",
    "NeonBuilding_4": "Asset/Json/NeonBuilding_4/constant.json",
    "NeonBuilding_5": "Asset/Json/NeonBuilding_5/constant.json",
    "NeonBuilding_6": "Asset/Json/NeonBuilding_6/constant.json",
    "NeonBuilding_7": "Asset/Json/NeonBuilding_7/constant.json",
    "Player": "Asset/Json/Player/constant.json",
    "Robot_1": "Asset/Json/Robot_1/constant.json",
    "Robot_2": "Asset/Json/Robot_2/constant.json",
    "Robot_3": "Asset/Json/Robot_3/constant.json"
  }
}